routescan/__init__.py
routescan/api_router.py
routescan/module_scanner.py
routescan/route_info.py
routescan/route_initializer.py
routescan/route_registrar.py
routescan/types.py
routescan-0.1.1a0.dist-info/LICENSE
routescan-0.1.1a0.dist-info/METADATA
routescan-0.1.1a0.dist-info/WHEEL
routescan-0.1.1a0.dist-info/top_level.txt
routescan-0.1.1a0.dist-info/RECORD
