Metadata-Version: 2.1
Name: routescan
Version: 0.1.1a0
Summary: Automatically scans and adds routes to app
Home-page: https://git.iec.io/ai/routescan
Author: wangyandong01
Author-email: wangyandong01@inspur.com
License: Copyright (c) 2017, Wangyandong
License-File: LICENSE
